{
  "annotations": {
    "list": [
      {
        "builtIn": 1,
        "datasource": {
          "type": "datasource",
          "uid": "grafana"
        },
        "enable": true,
        "hide": true,
        "iconColor": "rgba(0, 211, 255, 1)",
        "name": "Annotations & Alerts",
        "target": {
          "limit": 100,
          "matchAny": false,
          "tags": [],
          "type": "dashboard"
        },
        "type": "dashboard"
      }
    ]
  },
  "editable": true,
  "fiscalYearStartMonth": 0,
  "graphTooltip": 1,
  "id": 151,
  "iteration": 1717731753417,
  "links": [],
  "liveNow": false,
  "panels": [
    {
      "collapsed": false,
      "datasource": {
        "type": "datasource",
        "uid": "grafana"
      },
      "gridPos": {
        "h": 1,
        "w": 24,
        "x": 0,
        "y": 0
      },
      "id": 1135,
      "panels": [],
      "title": "概览",
      "type": "row"
    },
    {
      "datasource": {
        "type": "prometheus",
        "uid": "${data_source}"
      },
      "fieldConfig": {
        "defaults": {
          "color": {
            "mode": "thresholds"
          },
          "mappings": [
            {
              "options": {
                "from": 0,
                "result": {
                  "text": "严重"
                },
                "to": 0.9
              },
              "type": "range"
            },
            {
              "options": {
                "from": 0.9,
                "result": {
                  "text": "警告"
                },
                "to": 0.99
              },
              "type": "range"
            },
            {
              "options": {
                "from": 1,
                "result": {
                  "text": "健康"
                },
                "to": 1
              },
              "type": "range"
            }
          ],
          "thresholds": {
            "mode": "absolute",
            "steps": [
              {
                "color": "#E02F44",
                "value": null
              },
              {
                "color": "#FF780A",
                "value": 0.5
              },
              {
                "color": "#56A64B",
                "value": 1
              }
            ]
          },
          "unit": "none"
        },
        "overrides": []
      },
      "gridPos": {
        "h": 5,
        "w": 3,
        "x": 0,
        "y": 1
      },
      "id": 1133,
      "links": [],
      "maxDataPoints": 100,
      "options": {
        "colorMode": "background",
        "graphMode": "none",
        "justifyMode": "auto",
        "orientation": "horizontal",
        "reduceOptions": {
          "calcs": [
            "lastNotNull"
          ],
          "fields": "",
          "values": false
        },
        "textMode": "auto"
      },
      "pluginVersion": "8.5.22",
      "targets": [
        {
          "alias": "",
          "datasource": {
            "type": "prometheus",
            "uid": "${data_source}"
          },
          "dsType": "influxdb",
          "exemplar": true,
          "expr": "avg(up{kubernetes_pod_name=~\"$instance\",app=\"$workload\"})by(job)",
          "format": "time_series",
          "groupBy": [
            {
              "params": [
                "$interval"
              ],
              "type": "time"
            },
            {
              "params": [
                "null"
              ],
              "type": "fill"
            }
          ],
          "interval": "",
          "intervalFactor": 2,
          "legendFormat": "{{instance}}",
          "measurement": "application.httprequests__active",
          "policy": "default",
          "refId": "A",
          "resultFormat": "time_series",
          "select": [
            [
              {
                "params": [
                  "value"
                ],
                "type": "field"
              },
              {
                "params": [],
                "type": "last"
              }
            ]
          ],
          "step": 10,
          "tags": [
            {
              "key": "env",
              "operator": "=~",
              "value": "/^$environment$/"
            },
            {
              "condition": "AND",
              "key": "app",
              "operator": "=~",
              "value": "/^$application$/"
            }
          ]
        }
      ],
      "type": "stat"
    },
    {
      "datasource": {
        "type": "prometheus",
        "uid": "${data_source}"
      },
      "fieldConfig": {
        "defaults": {
          "mappings": [],
          "thresholds": {
            "mode": "absolute",
            "steps": [
              {
                "color": "green",
                "value": null
              },
              {
                "color": "red",
                "value": 80
              }
            ]
          }
        },
        "overrides": []
      },
      "gridPos": {
        "h": 5,
        "w": 3,
        "x": 3,
        "y": 1
      },
      "id": 36,
      "links": [],
      "options": {
        "colorMode": "value",
        "graphMode": "area",
        "justifyMode": "auto",
        "orientation": "auto",
        "reduceOptions": {
          "calcs": [
            "mean"
          ],
          "fields": "",
          "values": false
        },
        "text": {},
        "textMode": "auto"
      },
      "pluginVersion": "8.5.22",
      "targets": [
        {
          "alias": "",
          "datasource": {
            "type": "prometheus",
            "uid": "${data_source}"
          },
          "dsType": "influxdb",
          "exemplar": false,
          "expr": "sum(up{kubernetes_pod_name=~\"$instance\",kubernetes_namespace=\"$namespace\",version=\"$version\",app=\"$workload\"})",
          "format": "time_series",
          "groupBy": [
            {
              "params": [
                "$interval"
              ],
              "type": "time"
            },
            {
              "params": [
                "null"
              ],
              "type": "fill"
            }
          ],
          "instant": true,
          "interval": "",
          "intervalFactor": 2,
          "legendFormat": "{{instance}}",
          "measurement": "application.httprequests__active",
          "policy": "default",
          "refId": "A",
          "resultFormat": "time_series",
          "select": [
            [
              {
                "params": [
                  "value"
                ],
                "type": "field"
              },
              {
                "params": [],
                "type": "last"
              }
            ]
          ],
          "step": 10,
          "tags": [
            {
              "key": "env",
              "operator": "=~",
              "value": "/^$environment$/"
            },
            {
              "condition": "AND",
              "key": "app",
              "operator": "=~",
              "value": "/^$application$/"
            }
          ]
        }
      ],
      "title": "实例数",
      "type": "stat"
    },
    {
      "datasource": {
        "type": "prometheus",
        "uid": "${data_source}"
      },
      "description": "",
      "fieldConfig": {
        "defaults": {
          "color": {
            "mode": "thresholds"
          },
          "decimals": 2,
          "mappings": [
            {
              "options": {
                "match": "null",
                "result": {
                  "text": "N/A"
                }
              },
              "type": "special"
            }
          ],
          "max": 1,
          "min": 0,
          "thresholds": {
            "mode": "absolute",
            "steps": [
              {
                "color": "#299c46",
                "value": null
              },
              {
                "color": "rgba(237, 129, 40, 0.89)",
                "value": 0.5
              },
              {
                "color": "#d44a3a",
                "value": 0.8
              }
            ]
          },
          "unit": "percentunit"
        },
        "overrides": []
      },
      "gridPos": {
        "h": 5,
        "w": 3,
        "x": 6,
        "y": 1
      },
      "id": 1129,
      "links": [],
      "maxDataPoints": 100,
      "options": {
        "orientation": "horizontal",
        "reduceOptions": {
          "calcs": [
            "max"
          ],
          "fields": "",
          "values": false
        },
        "showThresholdLabels": false,
        "showThresholdMarkers": true
      },
      "pluginVersion": "8.5.22",
      "targets": [
        {
          "datasource": {
            "type": "prometheus",
            "uid": "${data_source}"
          },
          "exemplar": true,
          "expr": "max((irate(process_cpu_seconds_total{kubernetes_pod_name=~\"$instance\",kubernetes_namespace=\"$namespace\",app=\"$workload\"}[$summarize])  ) * 100)",
          "format": "time_series",
          "hide": true,
          "interval": "",
          "intervalFactor": 1,
          "legendFormat": "",
          "refId": "A"
        },
        {
          "datasource": {
            "type": "prometheus",
            "uid": "${data_source}"
          },
          "exemplar": true,
          "expr": "max (\nsum(node_namespace_pod_container:container_cpu_usage_seconds_total:sum_irate{namespace=\"$namespace\", pod=~\"$instance\", container!=\"POD\"}) by (pod,container)\n/\n(sum(\n    kube_pod_container_resource_limits{ resource=\"cpu\", namespace=\"$namespace\", pod=~\"$instance\"}) by (pod, container))\n)",
          "hide": false,
          "interval": "",
          "legendFormat": "",
          "refId": "B"
        }
      ],
      "title": "应用进程最大cpu",
      "type": "gauge"
    },
    {
      "datasource": {
        "type": "prometheus",
        "uid": "${data_source}"
      },
      "fieldConfig": {
        "defaults": {
          "mappings": [],
          "thresholds": {
            "mode": "absolute",
            "steps": [
              {
                "color": "green",
                "value": null
              },
              {
                "color": "red",
                "value": 80
              }
            ]
          },
          "unit": "bytes"
        },
        "overrides": []
      },
      "gridPos": {
        "h": 5,
        "w": 4,
        "x": 9,
        "y": 1
      },
      "id": 1130,
      "links": [],
      "options": {
        "colorMode": "value",
        "graphMode": "area",
        "justifyMode": "auto",
        "orientation": "auto",
        "reduceOptions": {
          "calcs": [
            "mean"
          ],
          "fields": "",
          "values": false
        },
        "text": {},
        "textMode": "auto"
      },
      "pluginVersion": "8.5.22",
      "targets": [
        {
          "datasource": {
            "type": "prometheus",
            "uid": "${data_source}"
          },
          "expr": "max(process_resident_memory_bytes{kubernetes_pod_name=~\"$instance\",kubernetes_namespace=\"$namespace\",app=\"$workload\"})\n",
          "format": "time_series",
          "interval": "",
          "intervalFactor": 1,
          "legendFormat": "",
          "refId": "A"
        }
      ],
      "title": "应用进程最大进程驻留内存",
      "type": "stat"
    },
    {
      "datasource": {
        "type": "prometheus",
        "uid": "${data_source}"
      },
      "fieldConfig": {
        "defaults": {
          "mappings": [],
          "thresholds": {
            "mode": "absolute",
            "steps": [
              {
                "color": "green",
                "value": null
              },
              {
                "color": "red",
                "value": 80
              }
            ]
          }
        },
        "overrides": []
      },
      "gridPos": {
        "h": 5,
        "w": 4,
        "x": 13,
        "y": 1
      },
      "id": 1131,
      "links": [],
      "options": {
        "colorMode": "value",
        "graphMode": "area",
        "justifyMode": "auto",
        "orientation": "auto",
        "reduceOptions": {
          "calcs": [
            "mean"
          ],
          "fields": "",
          "values": false
        },
        "text": {},
        "textMode": "auto"
      },
      "pluginVersion": "8.5.22",
      "targets": [
        {
          "datasource": {
            "type": "prometheus",
            "uid": "${data_source}"
          },
          "expr": "max(sum(irate(ego_server_handle_seconds_count{kubernetes_namespace=\"$namespace\", kubernetes_pod_name=~\"$instance\",app=\"$workload\"}[$summarize])) by (instance))",
          "format": "time_series",
          "interval": "",
          "intervalFactor": 1,
          "legendFormat": "{{$instance}}",
          "refId": "A"
        }
      ],
      "title": "单一实例最大QPS",
      "type": "stat"
    },
    {
      "datasource": {
        "type": "prometheus",
        "uid": "${data_source}"
      },
      "fieldConfig": {
        "defaults": {
          "mappings": [],
          "thresholds": {
            "mode": "absolute",
            "steps": [
              {
                "color": "green",
                "value": null
              },
              {
                "color": "red",
                "value": 80
              }
            ]
          }
        },
        "overrides": []
      },
      "gridPos": {
        "h": 5,
        "w": 4,
        "x": 17,
        "y": 1
      },
      "id": 1132,
      "links": [],
      "options": {
        "colorMode": "value",
        "graphMode": "area",
        "justifyMode": "auto",
        "orientation": "auto",
        "reduceOptions": {
          "calcs": [
            "mean"
          ],
          "fields": "",
          "values": false
        },
        "text": {},
        "textMode": "auto"
      },
      "pluginVersion": "8.5.22",
      "targets": [
        {
          "datasource": {
            "type": "prometheus",
            "uid": "${data_source}"
          },
          "expr": "max(sum(irate(ego_server_handle_seconds_count{kubernetes_pod_name=~\"$instance\",kubernetes_namespace=\"$namespace\",app=\"$workload\"}[$summarize])) by (job)) ",
          "format": "time_series",
          "interval": "",
          "intervalFactor": 1,
          "legendFormat": "总 QPS",
          "refId": "A"
        }
      ],
      "title": "总 QPS",
      "type": "stat"
    },
    {
      "datasource": {
        "type": "prometheus",
        "uid": "${data_source}"
      },
      "description": "",
      "fieldConfig": {
        "defaults": {
          "color": {
            "fixedColor": "rgb(31, 120, 193)",
            "mode": "fixed"
          },
          "mappings": [
            {
              "options": {
                "match": "null",
                "result": {
                  "text": "N/A"
                }
              },
              "type": "special"
            }
          ],
          "thresholds": {
            "mode": "absolute",
            "steps": [
              {
                "color": "green",
                "value": null
              },
              {
                "color": "red",
                "value": 80
              }
            ]
          },
          "unit": "none"
        },
        "overrides": []
      },
      "gridPos": {
        "h": 5,
        "w": 3,
        "x": 21,
        "y": 1
      },
      "id": 59,
      "links": [],
      "maxDataPoints": 100,
      "options": {
        "colorMode": "none",
        "graphMode": "area",
        "justifyMode": "auto",
        "orientation": "horizontal",
        "reduceOptions": {
          "calcs": [
            "mean"
          ],
          "fields": "",
          "values": false
        },
        "textMode": "auto"
      },
      "pluginVersion": "8.5.22",
      "targets": [
        {
          "datasource": {
            "type": "prometheus",
            "uid": "${data_source}"
          },
          "expr": "max(process_open_fds{kubernetes_namespace=\"$namespace\",app=\"$workload\"})by(job)",
          "format": "time_series",
          "hide": false,
          "interval": "",
          "intervalFactor": 1,
          "legendFormat": "{{instance}}",
          "refId": "A"
        }
      ],
      "title": "单一实例最大文件句柄数",
      "type": "stat"
    },
    {
      "aliasColors": {},
      "bars": false,
      "dashLength": 10,
      "dashes": false,
      "datasource": {
        "type": "prometheus",
        "uid": "P1809F7CD0C75ACF3"
      },
      "decimals": 2,
      "fieldConfig": {
        "defaults": {
          "links": []
        },
        "overrides": []
      },
      "fill": 1,
      "fillGradient": 0,
      "gridPos": {
        "h": 7,
        "w": 6,
        "x": 0,
        "y": 6
      },
      "hiddenSeries": false,
      "id": 1146,
      "legend": {
        "alignAsTable": true,
        "avg": true,
        "current": true,
        "max": true,
        "min": true,
        "rightSide": false,
        "show": true,
        "total": false,
        "values": true
      },
      "lines": true,
      "linewidth": 1,
      "links": [],
      "nullPointMode": "null",
      "options": {
        "alertThreshold": true
      },
      "percentage": false,
      "pluginVersion": "8.5.22",
      "pointradius": 2,
      "points": false,
      "renderer": "flot",
      "seriesOverrides": [],
      "spaceLength": 10,
      "stack": false,
      "steppedLine": false,
      "targets": [
        {
          "datasource": {
            "type": "prometheus",
            "uid": "P1809F7CD0C75ACF3"
          },
          "exemplar": true,
          "expr": "clamp_max(1-(\nsum(rate(ego_server_handle_total{type=~\"unary|stream\",app=\"$workload\",kubernetes_namespace=\"$namespace\",uniform_code=~\"$server_error_code\"}[$summarize]))/(sum(rate(ego_server_started_total{type=~\"unary|stream\",app=\"$workload\",app=~\"^($workload)$\",kubernetes_namespace=\"$namespace\"}[$summarize])) OR sum(rate(ego_server_handle_total{type=~\"unary|stream\",app=\"$workload\",app=~\"^($workload)$\",kubernetes_namespace=\"$namespace\"}[$summarize])))\n),1) OR vector(1)",
          "format": "time_series",
          "hide": false,
          "interval": "",
          "intervalFactor": 1,
          "legendFormat": "gRPC",
          "refId": "A"
        },
        {
          "datasource": {
            "type": "prometheus",
            "uid": "P1809F7CD0C75ACF3"
          },
          "exemplar": true,
          "expr": "clamp_max(1-(\nsum(irate(ego_server_handle_total{type=\"http\",app=\"$workload\",kubernetes_namespace=\"$namespace\",uniform_code=~\"$server_error_code\"}[$summarize]))/(sum(rate(ego_server_started_total{type=~\"http\",app=\"$workload\",kubernetes_namespace=\"$namespace\"}[$summarize])) OR sum(rate(ego_server_handle_total{type=~\"http\",app=\"$workload\",app=~\"^($workload)$\",kubernetes_namespace=\"$namespace\"}[$summarize])))\n),1) OR vector(1)",
          "hide": false,
          "interval": "",
          "legendFormat": "HTTP",
          "refId": "B"
        }
      ],
      "thresholds": [],
      "timeRegions": [],
      "title": "Server 端可用性",
      "tooltip": {
        "shared": true,
        "sort": 2,
        "value_type": "individual"
      },
      "type": "graph",
      "xaxis": {
        "mode": "time",
        "show": true,
        "values": []
      },
      "yaxes": [
        {
          "$$hashKey": "object:629",
          "decimals": 2,
          "format": "percentunit",
          "logBase": 1,
          "max": "1",
          "min": "0",
          "show": true
        },
        {
          "$$hashKey": "object:630",
          "decimals": 2,
          "format": "short",
          "logBase": 1,
          "min": "0",
          "show": false
        }
      ],
      "yaxis": {
        "align": false
      }
    },
    {
      "datasource": {
        "type": "prometheus",
        "uid": "${data_source}"
      },
      "fieldConfig": {
        "defaults": {
          "custom": {
            "align": "auto",
            "displayMode": "auto",
            "filterable": false,
            "inspect": false
          },
          "mappings": [],
          "thresholds": {
            "mode": "absolute",
            "steps": [
              {
                "color": "green",
                "value": null
              },
              {
                "color": "red",
                "value": 80
              }
            ]
          }
        },
        "overrides": [
          {
            "matcher": {
              "id": "byName",
              "options": "app_version"
            },
            "properties": [
              {
                "id": "custom.width",
                "value": 188
              }
            ]
          },
          {
            "matcher": {
              "id": "byName",
              "options": "kubernetes_pod_name"
            },
            "properties": [
              {
                "id": "custom.width",
                "value": 268
              }
            ]
          },
          {
            "matcher": {
              "id": "byName",
              "options": "应用版本"
            },
            "properties": [
              {
                "id": "custom.width",
                "value": 192
              }
            ]
          },
          {
            "matcher": {
              "id": "byName",
              "options": "version"
            },
            "properties": [
              {
                "id": "custom.width",
                "value": 85
              }
            ]
          },
          {
            "matcher": {
              "id": "byName",
              "options": "enable"
            },
            "properties": [
              {
                "id": "custom.width",
                "value": 66
              }
            ]
          },
          {
            "matcher": {
              "id": "byName",
              "options": "框架版本"
            },
            "properties": [
              {
                "id": "custom.width",
                "value": 95
              }
            ]
          },
          {
            "matcher": {
              "id": "byName",
              "options": "Go版本"
            },
            "properties": [
              {
                "id": "custom.width",
                "value": 84
              }
            ]
          },
          {
            "matcher": {
              "id": "byName",
              "options": "Namespace"
            },
            "properties": [
              {
                "id": "custom.width",
                "value": 107
              }
            ]
          }
        ]
      },
      "gridPos": {
        "h": 7,
        "w": 18,
        "x": 6,
        "y": 6
      },
      "id": 1137,
      "options": {
        "footer": {
          "fields": "",
          "reducer": [
            "sum"
          ],
          "show": false
        },
        "frameIndex": 1,
        "showHeader": true,
        "sortBy": []
      },
      "pluginVersion": "8.5.22",
      "repeatDirection": "h",
      "targets": [
        {
          "datasource": {
            "type": "prometheus",
            "uid": "${data_source}"
          },
          "exemplar": false,
          "expr": "ego_build_info{name=\"$appname\",app=\"$workload\",kubernetes_namespace=~\"$namespace\",version=\"$version\"}",
          "format": "table",
          "hide": false,
          "instant": true,
          "interval": "",
          "intervalFactor": 1,
          "legendFormat": "",
          "refId": "A"
        }
      ],
      "title": "Instance",
      "transformations": [
        {
          "id": "filterFieldsByName",
          "options": {
            "include": {
              "names": [
                "ego_version",
                "enable",
                "go_version",
                "instance",
                "kubernetes_namespace",
                "kubernetes_pod_name",
                "pod_template_hash",
                "start_time",
                "version",
                "app_version"
              ]
            }
          }
        },
        {
          "id": "organize",
          "options": {
            "excludeByName": {},
            "indexByName": {
              "app_version": 3,
              "build_time": 2,
              "ego_version": 4,
              "enable": 5,
              "go_version": 6,
              "instance": 7,
              "kubernetes_namespace": 8,
              "kubernetes_pod_name": 0,
              "pod_template_hash": 9,
              "start_time": 1,
              "version": 10
            },
            "renameByName": {
              "app_version": "应用版本",
              "build_time": "编译时间",
              "ego_version": "框架版本",
              "enable": "",
              "go_version": "Go版本",
              "instance": "Pod IP",
              "k8s_cluster": "",
              "kubernetes_namespace": "Namespace",
              "kubernetes_pod_name": "Pod",
              "pod_template_hash": "",
              "start_time": "启动时间",
              "version": ""
            }
          }
        }
      ],
      "type": "table"
    },
    {
      "datasource": {
        "type": "prometheus",
        "uid": "${data_source}"
      },
      "fieldConfig": {
        "defaults": {
          "color": {
            "mode": "palette-classic"
          },
          "custom": {
            "axisLabel": "",
            "axisPlacement": "auto",
            "barAlignment": 0,
            "drawStyle": "line",
            "fillOpacity": 100,
            "gradientMode": "opacity",
            "hideFrom": {
              "legend": false,
              "tooltip": false,
              "viz": false
            },
            "lineInterpolation": "smooth",
            "lineWidth": 1,
            "pointSize": 5,
            "scaleDistribution": {
              "type": "linear"
            },
            "showPoints": "never",
            "spanNulls": true,
            "stacking": {
              "group": "A",
              "mode": "none"
            },
            "thresholdsStyle": {
              "mode": "off"
            }
          },
          "links": [],
          "mappings": [],
          "thresholds": {
            "mode": "absolute",
            "steps": [
              {
                "color": "green",
                "value": null
              },
              {
                "color": "red",
                "value": 0.8
              }
            ]
          },
          "unit": "percentunit"
        },
        "overrides": []
      },
      "gridPos": {
        "h": 7,
        "w": 7,
        "x": 0,
        "y": 13
      },
      "id": 67,
      "interval": "$summarize",
      "links": [],
      "options": {
        "legend": {
          "calcs": [],
          "displayMode": "list",
          "placement": "bottom"
        },
        "tooltip": {
          "mode": "single",
          "sort": "none"
        }
      },
      "pluginVersion": "8.3.7",
      "targets": [
        {
          "alias": "",
          "datasource": {
            "type": "prometheus",
            "uid": "${data_source}"
          },
          "dsType": "influxdb",
          "exemplar": true,
          "expr": "max(irate(process_cpu_seconds_total{app=\"$workload\",kubernetes_namespace=\"$namespace\"}[$summarize]))by(instance)",
          "format": "time_series",
          "groupBy": [
            {
              "params": [
                "$interval"
              ],
              "type": "time"
            },
            {
              "params": [
                "null"
              ],
              "type": "fill"
            }
          ],
          "hide": true,
          "interval": "",
          "intervalFactor": 2,
          "legendFormat": "{{instance}}",
          "measurement": "application.httprequests__active",
          "policy": "default",
          "refId": "A",
          "resultFormat": "time_series",
          "select": [
            [
              {
                "params": [
                  "value"
                ],
                "type": "field"
              },
              {
                "params": [],
                "type": "last"
              }
            ]
          ],
          "step": 10,
          "tags": [
            {
              "key": "env",
              "operator": "=~",
              "value": "/^$environment$/"
            },
            {
              "condition": "AND",
              "key": "app",
              "operator": "=~",
              "value": "/^$application$/"
            }
          ]
        },
        {
          "datasource": {
            "type": "prometheus",
            "uid": "${data_source}"
          },
          "exemplar": true,
          "expr": "sum(node_namespace_pod_container:container_cpu_usage_seconds_total:sum_irate{namespace=\"$namespace\", pod=~\"$instance\", container!=\"POD\"}) by (pod,container)\n/\n(sum(\n    kube_pod_container_resource_limits{resource=\"cpu\", namespace=\"$namespace\", pod=~\"$instance\"}) by (pod, container))",
          "hide": false,
          "interval": "",
          "legendFormat": "{{pod}}/{{container}}",
          "refId": "B"
        }
      ],
      "title": "应用进程CPU使用率 limit（多实例）",
      "type": "timeseries"
    },
    {
      "datasource": {
        "type": "prometheus",
        "uid": "${data_source}"
      },
      "description": "Go程序占用的常驻内存和虚拟内存容量",
      "fieldConfig": {
        "defaults": {
          "color": {
            "mode": "palette-classic"
          },
          "custom": {
            "axisLabel": "",
            "axisPlacement": "auto",
            "barAlignment": 0,
            "drawStyle": "line",
            "fillOpacity": 100,
            "gradientMode": "opacity",
            "hideFrom": {
              "legend": false,
              "tooltip": false,
              "viz": false
            },
            "lineInterpolation": "smooth",
            "lineWidth": 1,
            "pointSize": 5,
            "scaleDistribution": {
              "type": "linear"
            },
            "showPoints": "never",
            "spanNulls": true,
            "stacking": {
              "group": "A",
              "mode": "none"
            },
            "thresholdsStyle": {
              "mode": "off"
            }
          },
          "links": [],
          "mappings": [],
          "thresholds": {
            "mode": "absolute",
            "steps": [
              {
                "color": "green",
                "value": null
              }
            ]
          },
          "unit": "decbytes"
        },
        "overrides": []
      },
      "gridPos": {
        "h": 7,
        "w": 8,
        "x": 7,
        "y": 13
      },
      "id": 66,
      "links": [],
      "options": {
        "legend": {
          "calcs": [],
          "displayMode": "list",
          "placement": "bottom"
        },
        "tooltip": {
          "mode": "single",
          "sort": "none"
        }
      },
      "pluginVersion": "8.3.7",
      "targets": [
        {
          "datasource": {
            "type": "prometheus",
            "uid": "${data_source}"
          },
          "exemplar": true,
          "expr": "sum(go_memstats_alloc_bytes{app=\"$workload\",kubernetes_namespace=\"$namespace\",kubernetes_pod_name=~\"$instance\"})by(kubernetes_pod_name)",
          "format": "time_series",
          "hide": false,
          "interval": "",
          "intervalFactor": 1,
          "legendFormat": "memstats_alloc | {{kubernetes_pod_name}} ",
          "refId": "A"
        },
        {
          "datasource": {
            "type": "prometheus",
            "uid": "${data_source}"
          },
          "expr": "sum(go_memstats_heap_inuse_bytes{app=\"$workload\",kubernetes_namespace=\"$namespace\",kubernetes_pod_name=~\"$instance\"})by(kubernetes_pod_name)",
          "format": "time_series",
          "hide": false,
          "interval": "",
          "intervalFactor": 1,
          "legendFormat": "heap_inuse | {{kubernetes_pod_name}} ",
          "refId": "B"
        },
        {
          "datasource": {
            "type": "prometheus",
            "uid": "${data_source}"
          },
          "expr": "sum(go_memstats_stack_inuse_bytes{app=~\"^($workload)$\",kubernetes_pod_name=~\"$instance\"})by(kubernetes_pod_name)",
          "format": "time_series",
          "hide": false,
          "interval": "",
          "intervalFactor": 1,
          "legendFormat": " stack_inuse | {{kubernetes_pod_name}}",
          "refId": "C"
        },
        {
          "datasource": {
            "type": "prometheus",
            "uid": "${data_source}"
          },
          "expr": "sum(go_memstats_sys_bytes{app=~\"^($workload)$\",kubernetes_pod_name=~\"$instance\"})by(kubernetes_pod_name)",
          "format": "time_series",
          "hide": false,
          "interval": "",
          "intervalFactor": 1,
          "legendFormat": "memstats_sys | {{kubernetes_pod_name}} ",
          "refId": "D"
        },
        {
          "datasource": {
            "type": "prometheus",
            "uid": "${data_source}"
          },
          "expr": "sum(process_resident_memory_bytes{app=~\"^($workload)$\",kubernetes_pod_name=~\"$podname\"})by(kubernetes_pod_name)",
          "format": "time_series",
          "interval": "",
          "intervalFactor": 1,
          "legendFormat": "总进程驻留内存 | {{kubernetes_pod_name}}  ",
          "refId": "E"
        },
        {
          "datasource": {
            "type": "prometheus",
            "uid": "${data_source}"
          },
          "editorMode": "code",
          "expr": "sum(nodejs_heap_space_size_used_bytes{app=~\"^($workload)$\",kubernetes_pod_name=~\"$podname\"})by(kubernetes_pod_name)",
          "hide": false,
          "legendFormat": "heap_inuse | {{kubernetes_pod_name}}",
          "range": true,
          "refId": "F"
        },
        {
          "datasource": {
            "type": "prometheus",
            "uid": "${data_source}"
          },
          "editorMode": "code",
          "expr": "sum(go_memstats_heap_idle_bytes{app=\"$workload\",kubernetes_namespace=\"$namespace\",kubernetes_pod_name=~\"$instance\"})by(kubernetes_pod_name)",
          "format": "time_series",
          "hide": false,
          "interval": "",
          "intervalFactor": 1,
          "legendFormat": "heap_idle | {{kubernetes_pod_name}} ",
          "range": true,
          "refId": "G"
        },
        {
          "datasource": {
            "type": "prometheus",
            "uid": "${data_source}"
          },
          "editorMode": "code",
          "expr": "sum(go_memstats_heap_released_bytes{app=\"$workload\",kubernetes_namespace=\"$namespace\",kubernetes_pod_name=~\"$instance\"})by(kubernetes_pod_name)",
          "format": "time_series",
          "hide": false,
          "interval": "",
          "intervalFactor": 1,
          "legendFormat": "heap_released | {{kubernetes_pod_name}} ",
          "range": true,
          "refId": "H"
        }
      ],
      "title": "应用内存信息（多实例）",
      "type": "timeseries"
    },
    {
      "datasource": {
        "type": "prometheus",
        "uid": "${data_source}"
      },
      "description": "Go程序占用连接信息",
      "fieldConfig": {
        "defaults": {
          "color": {
            "mode": "palette-classic"
          },
          "custom": {
            "axisLabel": "",
            "axisPlacement": "auto",
            "barAlignment": 0,
            "drawStyle": "line",
            "fillOpacity": 100,
            "gradientMode": "opacity",
            "hideFrom": {
              "legend": false,
              "tooltip": false,
              "viz": false
            },
            "lineInterpolation": "smooth",
            "lineWidth": 1,
            "pointSize": 5,
            "scaleDistribution": {
              "type": "linear"
            },
            "showPoints": "never",
            "spanNulls": true,
            "stacking": {
              "group": "A",
              "mode": "none"
            },
            "thresholdsStyle": {
              "mode": "off"
            }
          },
          "links": [],
          "mappings": [],
          "thresholds": {
            "mode": "absolute",
            "steps": [
              {
                "color": "green",
                "value": null
              }
            ]
          },
          "unit": "none"
        },
        "overrides": []
      },
      "gridPos": {
        "h": 7,
        "w": 9,
        "x": 15,
        "y": 13
      },
      "id": 1147,
      "links": [],
      "options": {
        "legend": {
          "calcs": [],
          "displayMode": "list",
          "placement": "bottom"
        },
        "tooltip": {
          "mode": "single",
          "sort": "none"
        }
      },
      "pluginVersion": "8.3.7",
      "targets": [
        {
          "datasource": {
            "type": "prometheus",
            "uid": "${data_source}"
          },
          "editorMode": "code",
          "expr": "sum(ego_client_stats_gauge{type=\"conn_states\",app=\"$workload\",kubernetes_namespace=\"$namespace\",kubernetes_pod_name=~\"$instance\", index=\"established\",version=\"$version\"})by(name)",
          "hide": false,
          "legendFormat": "established_{{name}}",
          "range": true,
          "refId": "B"
        },
        {
          "datasource": {
            "type": "prometheus",
            "uid": "${data_source}"
          },
          "editorMode": "code",
          "expr": "sum(ego_client_stats_gauge{type=\"conn_states\",app=\"$workload\",kubernetes_namespace=\"$namespace\",kubernetes_pod_name=~\"$instance\", index=\"time_wait\",version=\"$version\"})by(name)",
          "hide": false,
          "legendFormat": "time_wait_{{name}}",
          "range": true,
          "refId": "C"
        }
      ],
      "title": "应用连接信息（多实例）",
      "type": "timeseries"
    },
    {
      "datasource": {
        "type": "prometheus",
        "uid": "${data_source}"
      },
      "fieldConfig": {
        "defaults": {
          "color": {
            "mode": "palette-classic"
          },
          "custom": {
            "axisLabel": "",
            "axisPlacement": "auto",
            "barAlignment": 0,
            "drawStyle": "line",
            "fillOpacity": 100,
            "gradientMode": "opacity",
            "hideFrom": {
              "legend": false,
              "tooltip": false,
              "viz": false
            },
            "lineInterpolation": "smooth",
            "lineWidth": 1,
            "pointSize": 5,
            "scaleDistribution": {
              "type": "linear"
            },
            "showPoints": "never",
            "spanNulls": true,
            "stacking": {
              "group": "A",
              "mode": "none"
            },
            "thresholdsStyle": {
              "mode": "off"
            }
          },
          "links": [],
          "mappings": [],
          "thresholds": {
            "mode": "absolute",
            "steps": [
              {
                "color": "green",
                "value": null
              },
              {
                "color": "red",
                "value": 80
              }
            ]
          },
          "unit": "short"
        },
        "overrides": []
      },
      "gridPos": {
        "h": 8,
        "w": 8,
        "x": 0,
        "y": 20
      },
      "id": 42,
      "interval": "$summarize",
      "links": [],
      "options": {
        "legend": {
          "calcs": [],
          "displayMode": "list",
          "placement": "bottom"
        },
        "tooltip": {
          "mode": "single",
          "sort": "none"
        }
      },
      "pluginVersion": "8.3.7",
      "targets": [
        {
          "alias": "",
          "datasource": {
            "type": "prometheus",
            "uid": "${data_source}"
          },
          "dsType": "influxdb",
          "exemplar": true,
          "expr": "max(go_goroutines{app=\"$workload\",kubernetes_namespace=\"$namespace\",kubernetes_pod_name=~\"$instance\"})by(kubernetes_pod_name)",
          "format": "time_series",
          "groupBy": [
            {
              "params": [
                "$interval"
              ],
              "type": "time"
            },
            {
              "params": [
                "null"
              ],
              "type": "fill"
            }
          ],
          "interval": "",
          "intervalFactor": 2,
          "legendFormat": "{{kubernetes_pod_name}}",
          "measurement": "application.httprequests__active",
          "policy": "default",
          "refId": "A",
          "resultFormat": "time_series",
          "select": [
            [
              {
                "params": [
                  "value"
                ],
                "type": "field"
              },
              {
                "params": [],
                "type": "last"
              }
            ]
          ],
          "step": 10,
          "tags": [
            {
              "key": "env",
              "operator": "=~",
              "value": "/^$environment$/"
            },
            {
              "condition": "AND",
              "key": "app",
              "operator": "=~",
              "value": "/^$application$/"
            }
          ]
        }
      ],
      "title": "Go Goroutines（多实例）",
      "type": "timeseries"
    },
    {
      "datasource": {
        "type": "prometheus",
        "uid": "${data_source}"
      },
      "description": "文件句柄数",
      "fieldConfig": {
        "defaults": {
          "color": {
            "mode": "palette-classic"
          },
          "custom": {
            "axisLabel": "",
            "axisPlacement": "auto",
            "barAlignment": 0,
            "drawStyle": "line",
            "fillOpacity": 100,
            "gradientMode": "opacity",
            "hideFrom": {
              "legend": false,
              "tooltip": false,
              "viz": false
            },
            "lineInterpolation": "smooth",
            "lineWidth": 1,
            "pointSize": 5,
            "scaleDistribution": {
              "type": "linear"
            },
            "showPoints": "never",
            "spanNulls": true,
            "stacking": {
              "group": "A",
              "mode": "none"
            },
            "thresholdsStyle": {
              "mode": "off"
            }
          },
          "links": [],
          "mappings": [],
          "thresholds": {
            "mode": "absolute",
            "steps": [
              {
                "color": "green",
                "value": null
              },
              {
                "color": "red",
                "value": 80
              }
            ]
          },
          "unit": "none"
        },
        "overrides": []
      },
      "gridPos": {
        "h": 8,
        "w": 8,
        "x": 8,
        "y": 20
      },
      "id": 57,
      "links": [],
      "options": {
        "legend": {
          "calcs": [],
          "displayMode": "list",
          "placement": "bottom"
        },
        "tooltip": {
          "mode": "single",
          "sort": "none"
        }
      },
      "pluginVersion": "8.3.7",
      "targets": [
        {
          "datasource": {
            "type": "prometheus",
            "uid": "${data_source}"
          },
          "exemplar": true,
          "expr": "process_open_fds{app=\"$workload\",kubernetes_namespace=\"$namespace\",kubernetes_pod_name=~\"$instance\"}",
          "format": "time_series",
          "hide": false,
          "interval": "",
          "intervalFactor": 1,
          "legendFormat": "{{kubernetes_pod_name}}",
          "refId": "A"
        }
      ],
      "title": "实例文件句柄数（多实例）",
      "type": "timeseries"
    },
    {
      "datasource": {
        "type": "prometheus",
        "uid": "${data_source}"
      },
      "description": "",
      "fieldConfig": {
        "defaults": {
          "color": {
            "mode": "palette-classic"
          },
          "custom": {
            "axisLabel": "",
            "axisPlacement": "auto",
            "barAlignment": 0,
            "drawStyle": "line",
            "fillOpacity": 100,
            "gradientMode": "opacity",
            "hideFrom": {
              "legend": false,
              "tooltip": false,
              "viz": false
            },
            "lineInterpolation": "smooth",
            "lineWidth": 1,
            "pointSize": 5,
            "scaleDistribution": {
              "type": "linear"
            },
            "showPoints": "never",
            "spanNulls": true,
            "stacking": {
              "group": "A",
              "mode": "none"
            },
            "thresholdsStyle": {
              "mode": "off"
            }
          },
          "links": [],
          "mappings": [],
          "thresholds": {
            "mode": "absolute",
            "steps": [
              {
                "color": "green",
                "value": null
              },
              {
                "color": "red",
                "value": 80
              }
            ]
          },
          "unit": "s"
        },
        "overrides": []
      },
      "gridPos": {
        "h": 8,
        "w": 8,
        "x": 16,
        "y": 20
      },
      "id": 68,
      "links": [],
      "options": {
        "legend": {
          "calcs": [],
          "displayMode": "list",
          "placement": "bottom"
        },
        "tooltip": {
          "mode": "single",
          "sort": "none"
        }
      },
      "pluginVersion": "8.3.7",
      "targets": [
        {
          "datasource": {
            "type": "prometheus",
            "uid": "${data_source}"
          },
          "exemplar": true,
          "expr": "max(go_gc_duration_seconds{app=\"$workload\",kubernetes_namespace=\"$namespace\",kubernetes_pod_name=~\"$instance\"})by(kubernetes_pod_name)",
          "format": "time_series",
          "hide": false,
          "interval": "",
          "intervalFactor": 1,
          "legendFormat": "{{kubernetes_pod_name}}",
          "refId": "A"
        },
        {
          "datasource": {
            "type": "prometheus",
            "uid": "${data_source}"
          },
          "editorMode": "code",
          "expr": "max by (kind) (\n    rate(\n        nodejs_gc_duration_seconds_sum{kubernetes_namespace=\"$namespace\",kubernetes_pod_name=~\"$instance\"}[1m]) \n        / rate(nodejs_gc_duration_seconds_count{kubernetes_namespace=\"$namespace\",kubernetes_pod_name=~\"$instance\"}[1m])\n)",
          "hide": false,
          "legendFormat": "{{kind}}",
          "range": true,
          "refId": "B"
        }
      ],
      "title": "GC 耗时",
      "type": "timeseries"
    },
    {
      "collapsed": false,
      "datasource": {
        "type": "datasource",
        "uid": "grafana"
      },
      "gridPos": {
        "h": 1,
        "w": 24,
        "x": 0,
        "y": 28
      },
      "id": 1112,
      "panels": [],
      "title": "服务端",
      "type": "row"
    },
    {
      "aliasColors": {},
      "bars": false,
      "dashLength": 10,
      "dashes": false,
      "datasource": {
        "type": "prometheus",
        "uid": "${data_source}"
      },
      "fieldConfig": {
        "defaults": {
          "links": []
        },
        "overrides": []
      },
      "fill": 1,
      "fillGradient": 0,
      "gridPos": {
        "h": 7,
        "w": 6,
        "x": 0,
        "y": 29
      },
      "hiddenSeries": false,
      "id": 1123,
      "legend": {
        "avg": false,
        "current": false,
        "max": false,
        "min": false,
        "show": true,
        "total": false,
        "values": false
      },
      "lines": true,
      "linewidth": 1,
      "links": [],
      "nullPointMode": "null",
      "options": {
        "alertThreshold": true
      },
      "percentage": false,
      "pluginVersion": "8.5.22",
      "pointradius": 2,
      "points": false,
      "renderer": "flot",
      "seriesOverrides": [],
      "spaceLength": 10,
      "stack": false,
      "steppedLine": false,
      "targets": [
        {
          "datasource": {
            "type": "prometheus",
            "uid": "${data_source}"
          },
          "editorMode": "code",
          "exemplar": true,
          "expr": "sum(irate(ego_server_handle_total{type=\"http\",app=\"$workload\",kubernetes_namespace=\"$namespace\"}[$summarize]))by(uniform_code,method)",
          "format": "time_series",
          "interval": "",
          "intervalFactor": 1,
          "legendFormat": "{{uniform_code}} | {{method}}",
          "range": true,
          "refId": "A"
        }
      ],
      "thresholds": [],
      "timeRegions": [],
      "title": "HTTP 服务端错误码分布",
      "tooltip": {
        "shared": true,
        "sort": 2,
        "value_type": "individual"
      },
      "type": "graph",
      "xaxis": {
        "mode": "time",
        "show": true,
        "values": []
      },
      "yaxes": [
        {
          "$$hashKey": "object:287",
          "decimals": 0,
          "format": "short",
          "logBase": 1,
          "min": "0",
          "show": true
        },
        {
          "$$hashKey": "object:288",
          "format": "short",
          "logBase": 1,
          "min": "0",
          "show": true
        }
      ],
      "yaxis": {
        "align": false
      }
    },
    {
      "aliasColors": {},
      "bars": false,
      "dashLength": 10,
      "dashes": false,
      "datasource": {
        "type": "prometheus",
        "uid": "${data_source}"
      },
      "fieldConfig": {
        "defaults": {
          "links": []
        },
        "overrides": []
      },
      "fill": 1,
      "fillGradient": 0,
      "gridPos": {
        "h": 7,
        "w": 9,
        "x": 6,
        "y": 29
      },
      "hiddenSeries": false,
      "id": 1115,
      "legend": {
        "avg": false,
        "current": false,
        "max": false,
        "min": false,
        "show": true,
        "total": false,
        "values": false
      },
      "lines": true,
      "linewidth": 1,
      "links": [],
      "nullPointMode": "null",
      "options": {
        "alertThreshold": true
      },
      "percentage": false,
      "pluginVersion": "8.5.22",
      "pointradius": 2,
      "points": false,
      "renderer": "flot",
      "seriesOverrides": [],
      "spaceLength": 10,
      "stack": false,
      "steppedLine": false,
      "targets": [
        {
          "datasource": {
            "type": "prometheus",
            "uid": "${data_source}"
          },
          "exemplar": true,
          "expr": "sum(irate(ego_server_handle_seconds_count{type=\"http\",app=\"$workload\",kubernetes_namespace=\"$namespace\"}[$summarize]))by(method)",
          "format": "time_series",
          "interval": "",
          "intervalFactor": 1,
          "legendFormat": "{{method}}",
          "refId": "A"
        }
      ],
      "thresholds": [],
      "timeRegions": [],
      "title": "HTTP 服务端QPS",
      "tooltip": {
        "shared": true,
        "sort": 2,
        "value_type": "individual"
      },
      "type": "graph",
      "xaxis": {
        "mode": "time",
        "show": true,
        "values": []
      },
      "yaxes": [
        {
          "$$hashKey": "object:151",
          "decimals": 0,
          "format": "short",
          "logBase": 1,
          "min": "0",
          "show": true
        },
        {
          "$$hashKey": "object:152",
          "format": "short",
          "logBase": 1,
          "min": "0",
          "show": true
        }
      ],
      "yaxis": {
        "align": false
      }
    },
    {
      "datasource": {
        "type": "prometheus",
        "uid": "${data_source}"
      },
      "fieldConfig": {
        "defaults": {
          "color": {
            "mode": "palette-classic"
          },
          "custom": {
            "axisLabel": "",
            "axisPlacement": "auto",
            "barAlignment": 0,
            "drawStyle": "line",
            "fillOpacity": 10,
            "gradientMode": "none",
            "hideFrom": {
              "legend": false,
              "tooltip": false,
              "viz": false
            },
            "lineInterpolation": "linear",
            "lineWidth": 1,
            "pointSize": 5,
            "scaleDistribution": {
              "type": "linear"
            },
            "showPoints": "never",
            "spanNulls": false,
            "stacking": {
              "group": "A",
              "mode": "none"
            },
            "thresholdsStyle": {
              "mode": "off"
            }
          },
          "decimals": 2,
          "links": [],
          "mappings": [],
          "min": 0,
          "thresholds": {
            "mode": "absolute",
            "steps": [
              {
                "color": "green",
                "value": null
              },
              {
                "color": "red",
                "value": 80
              }
            ]
          },
          "unit": "ms"
        },
        "overrides": []
      },
      "gridPos": {
        "h": 7,
        "w": 9,
        "x": 15,
        "y": 29
      },
      "id": 1122,
      "links": [],
      "options": {
        "legend": {
          "calcs": [],
          "displayMode": "list",
          "placement": "bottom"
        },
        "tooltip": {
          "mode": "single",
          "sort": "none"
        }
      },
      "pluginVersion": "8.3.7",
      "targets": [
        {
          "datasource": {
            "type": "prometheus",
            "uid": "${data_source}"
          },
          "editorMode": "code",
          "expr": "avg(histogram_quantile(0.99,irate(ego_server_handle_seconds_bucket{type=\"http\",app=\"$workload\",kubernetes_namespace=\"$namespace\"}[$summarize])>0)*1000)by(method)",
          "hide": false,
          "legendFormat": "{{method}}",
          "range": true,
          "refId": "A"
        }
      ],
      "title": "HTTP 服务端 P99",
      "type": "timeseries"
    },
    {
      "aliasColors": {},
      "bars": false,
      "dashLength": 10,
      "dashes": false,
      "datasource": {
        "type": "prometheus",
        "uid": "${data_source}"
      },
      "fieldConfig": {
        "defaults": {
          "links": []
        },
        "overrides": []
      },
      "fill": 1,
      "fillGradient": 0,
      "gridPos": {
        "h": 7,
        "w": 6,
        "x": 0,
        "y": 36
      },
      "hiddenSeries": false,
      "id": 1117,
      "legend": {
        "avg": false,
        "current": false,
        "max": false,
        "min": false,
        "show": true,
        "total": false,
        "values": false
      },
      "lines": true,
      "linewidth": 1,
      "links": [],
      "nullPointMode": "null",
      "options": {
        "alertThreshold": true
      },
      "percentage": false,
      "pluginVersion": "8.5.22",
      "pointradius": 2,
      "points": false,
      "renderer": "flot",
      "seriesOverrides": [],
      "spaceLength": 10,
      "stack": false,
      "steppedLine": false,
      "targets": [
        {
          "datasource": {
            "type": "prometheus",
            "uid": "${data_source}"
          },
          "editorMode": "code",
          "exemplar": true,
          "expr": "sum(rate(ego_server_handle_total{type=\"unary\",app=\"$workload\",kubernetes_namespace=\"$namespace\",uniform_code=~\"5.*\"}[$summarize]))by(uniform_code,method,instance)",
          "format": "time_series",
          "interval": "",
          "intervalFactor": 1,
          "legendFormat": "{{uniform_code}} | {{method}} ",
          "range": true,
          "refId": "A"
        }
      ],
      "thresholds": [],
      "timeRegions": [],
      "title": "gRPC 服务端异常状态码",
      "tooltip": {
        "shared": true,
        "sort": 2,
        "value_type": "individual"
      },
      "type": "graph",
      "xaxis": {
        "mode": "time",
        "show": true,
        "values": []
      },
      "yaxes": [
        {
          "$$hashKey": "object:629",
          "decimals": 0,
          "format": "short",
          "logBase": 1,
          "min": "0",
          "show": true
        },
        {
          "$$hashKey": "object:630",
          "format": "short",
          "logBase": 1,
          "min": "0",
          "show": true
        }
      ],
      "yaxis": {
        "align": false
      }
    },
    {
      "datasource": {
        "type": "prometheus",
        "uid": "${data_source}"
      },
      "fieldConfig": {
        "defaults": {
          "color": {
            "mode": "palette-classic"
          },
          "custom": {
            "axisLabel": "",
            "axisPlacement": "auto",
            "barAlignment": 0,
            "drawStyle": "line",
            "fillOpacity": 100,
            "gradientMode": "opacity",
            "hideFrom": {
              "legend": false,
              "tooltip": false,
              "viz": false
            },
            "lineInterpolation": "smooth",
            "lineWidth": 1,
            "pointSize": 5,
            "scaleDistribution": {
              "type": "linear"
            },
            "showPoints": "never",
            "spanNulls": true,
            "stacking": {
              "group": "A",
              "mode": "none"
            },
            "thresholdsStyle": {
              "mode": "off"
            }
          },
          "decimals": 2,
          "links": [],
          "mappings": [],
          "min": 0,
          "thresholds": {
            "mode": "absolute",
            "steps": [
              {
                "color": "green",
                "value": null
              },
              {
                "color": "red",
                "value": 80
              }
            ]
          },
          "unit": "short"
        },
        "overrides": []
      },
      "gridPos": {
        "h": 7,
        "w": 9,
        "x": 6,
        "y": 36
      },
      "id": 1127,
      "links": [],
      "options": {
        "legend": {
          "calcs": [],
          "displayMode": "list",
          "placement": "bottom"
        },
        "tooltip": {
          "mode": "single",
          "sort": "none"
        }
      },
      "pluginVersion": "8.3.7",
      "targets": [
        {
          "datasource": {
            "type": "prometheus",
            "uid": "${data_source}"
          },
          "exemplar": true,
          "expr": "sum(irate(ego_server_handle_total{type=~\"unary|stream\",app=\"$workload\",kubernetes_namespace=\"$namespace\"}[$summarize]))by(method)",
          "format": "time_series",
          "hide": false,
          "interval": "",
          "intervalFactor": 1,
          "legendFormat": " {{method}}",
          "refId": "A"
        }
      ],
      "title": "gRPC 服务端 QPS",
      "type": "timeseries"
    },
    {
      "datasource": {
        "type": "prometheus",
        "uid": "P1809F7CD0C75ACF3"
      },
      "fieldConfig": {
        "defaults": {
          "color": {
            "mode": "palette-classic"
          },
          "custom": {
            "axisLabel": "",
            "axisPlacement": "auto",
            "barAlignment": 0,
            "drawStyle": "line",
            "fillOpacity": 100,
            "gradientMode": "opacity",
            "hideFrom": {
              "legend": false,
              "tooltip": false,
              "viz": false
            },
            "lineInterpolation": "smooth",
            "lineWidth": 1,
            "pointSize": 5,
            "scaleDistribution": {
              "type": "linear"
            },
            "showPoints": "never",
            "spanNulls": false,
            "stacking": {
              "group": "A",
              "mode": "none"
            },
            "thresholdsStyle": {
              "mode": "off"
            }
          },
          "decimals": 2,
          "links": [],
          "mappings": [],
          "min": 0,
          "thresholds": {
            "mode": "absolute",
            "steps": [
              {
                "color": "green",
                "value": null
              },
              {
                "color": "red",
                "value": 80
              }
            ]
          },
          "unit": "ms"
        },
        "overrides": []
      },
      "gridPos": {
        "h": 7,
        "w": 9,
        "x": 15,
        "y": 36
      },
      "id": 1116,
      "links": [],
      "options": {
        "legend": {
          "calcs": [],
          "displayMode": "list",
          "placement": "bottom"
        },
        "tooltip": {
          "mode": "single",
          "sort": "none"
        }
      },
      "pluginVersion": "8.3.7",
      "targets": [
        {
          "datasource": {
            "type": "prometheus",
            "uid": "P1809F7CD0C75ACF3"
          },
          "editorMode": "code",
          "expr": "avg(histogram_quantile(0.99,irate(ego_server_handle_seconds_bucket{type=~\"unary|stream\",app=\"$workload\",kubernetes_namespace=\"$namespace\"}[$summarize])>0)*1000)by(method)",
          "hide": false,
          "legendFormat": "{{method}}",
          "range": true,
          "refId": "B"
        }
      ],
      "title": "gRPC 服务端 P99",
      "type": "timeseries"
    },
    {
      "collapsed": false,
      "datasource": {
        "type": "datasource",
        "uid": "grafana"
      },
      "gridPos": {
        "h": 1,
        "w": 24,
        "x": 0,
        "y": 43
      },
      "id": 1145,
      "panels": [],
      "title": "客户端",
      "type": "row"
    },
    {
      "aliasColors": {},
      "bars": false,
      "dashLength": 10,
      "dashes": false,
      "datasource": {
        "type": "prometheus",
        "uid": "P1809F7CD0C75ACF3"
      },
      "fill": 1,
      "fillGradient": 0,
      "gridPos": {
        "h": 8,
        "w": 6,
        "x": 0,
        "y": 44
      },
      "hiddenSeries": false,
      "id": 1141,
      "legend": {
        "avg": false,
        "current": false,
        "max": false,
        "min": false,
        "show": true,
        "total": false,
        "values": false
      },
      "lines": true,
      "linewidth": 1,
      "nullPointMode": "null as zero",
      "options": {
        "alertThreshold": true
      },
      "percentage": false,
      "pluginVersion": "8.5.22",
      "pointradius": 2,
      "points": false,
      "renderer": "flot",
      "seriesOverrides": [],
      "spaceLength": 10,
      "stack": false,
      "steppedLine": false,
      "targets": [
        {
          "datasource": {
            "type": "prometheus",
            "uid": "P1809F7CD0C75ACF3"
          },
          "exemplar": true,
          "expr": "sum(irate(ego_client_handle_total{type=\"unary\",app=\"$workload\",kubernetes_namespace=\"$namespace\",code!=\"OK\"}[$summarize]))by(code,method)",
          "interval": "",
          "legendFormat": "{{code}} | {{method}}",
          "refId": "A"
        }
      ],
      "thresholds": [],
      "timeRegions": [],
      "title": "gRPC 客户端错误码分布",
      "tooltip": {
        "shared": true,
        "sort": 0,
        "value_type": "individual"
      },
      "type": "graph",
      "xaxis": {
        "mode": "time",
        "show": true,
        "values": []
      },
      "yaxes": [
        {
          "$$hashKey": "object:716",
          "format": "short",
          "logBase": 1,
          "min": "0",
          "show": true
        },
        {
          "$$hashKey": "object:717",
          "format": "short",
          "logBase": 1,
          "min": "0",
          "show": true
        }
      ],
      "yaxis": {
        "align": false
      }
    },
    {
      "aliasColors": {},
      "bars": false,
      "dashLength": 10,
      "dashes": false,
      "datasource": {
        "type": "prometheus",
        "uid": "P1809F7CD0C75ACF3"
      },
      "fieldConfig": {
        "defaults": {
          "links": []
        },
        "overrides": []
      },
      "fill": 1,
      "fillGradient": 0,
      "gridPos": {
        "h": 8,
        "w": 9,
        "x": 6,
        "y": 44
      },
      "hiddenSeries": false,
      "id": 1142,
      "legend": {
        "avg": false,
        "current": false,
        "max": false,
        "min": false,
        "show": true,
        "total": false,
        "values": false
      },
      "lines": true,
      "linewidth": 1,
      "links": [],
      "nullPointMode": "null as zero",
      "options": {
        "alertThreshold": true
      },
      "percentage": false,
      "pluginVersion": "8.5.22",
      "pointradius": 2,
      "points": false,
      "renderer": "flot",
      "seriesOverrides": [],
      "spaceLength": 10,
      "stack": false,
      "steppedLine": false,
      "targets": [
        {
          "datasource": {
            "type": "prometheus",
            "uid": "P1809F7CD0C75ACF3"
          },
          "expr": "sum(irate(ego_client_handle_seconds_count{type=\"unary\",app=\"$workload\",kubernetes_namespace=\"$namespace\"}[$summarize]))by(name,method)",
          "format": "time_series",
          "interval": "",
          "intervalFactor": 1,
          "legendFormat": " {{name}}-{{method}}",
          "refId": "A"
        }
      ],
      "thresholds": [],
      "timeRegions": [],
      "title": "gRPC 客户端 QPS",
      "tooltip": {
        "shared": true,
        "sort": 2,
        "value_type": "individual"
      },
      "type": "graph",
      "xaxis": {
        "mode": "time",
        "show": true,
        "values": []
      },
      "yaxes": [
        {
          "$$hashKey": "object:687",
          "decimals": 0,
          "format": "short",
          "logBase": 1,
          "min": "0",
          "show": true
        },
        {
          "$$hashKey": "object:688",
          "format": "short",
          "logBase": 1,
          "min": "0",
          "show": true
        }
      ],
      "yaxis": {
        "align": false
      }
    },
    {
      "datasource": {
        "type": "prometheus",
        "uid": "P1809F7CD0C75ACF3"
      },
      "description": "",
      "fieldConfig": {
        "defaults": {
          "color": {
            "mode": "palette-classic"
          },
          "custom": {
            "axisLabel": "",
            "axisPlacement": "auto",
            "barAlignment": 0,
            "drawStyle": "line",
            "fillOpacity": 10,
            "gradientMode": "none",
            "hideFrom": {
              "legend": false,
              "tooltip": false,
              "viz": false
            },
            "lineInterpolation": "linear",
            "lineWidth": 1,
            "pointSize": 5,
            "scaleDistribution": {
              "type": "linear"
            },
            "showPoints": "never",
            "spanNulls": false,
            "stacking": {
              "group": "A",
              "mode": "none"
            },
            "thresholdsStyle": {
              "mode": "off"
            }
          },
          "decimals": 2,
          "links": [],
          "mappings": [],
          "min": 0,
          "thresholds": {
            "mode": "absolute",
            "steps": [
              {
                "color": "green",
                "value": null
              },
              {
                "color": "red",
                "value": 80
              }
            ]
          },
          "unit": "ms"
        },
        "overrides": []
      },
      "gridPos": {
        "h": 8,
        "w": 9,
        "x": 15,
        "y": 44
      },
      "id": 1143,
      "links": [],
      "options": {
        "legend": {
          "calcs": [],
          "displayMode": "list",
          "placement": "bottom"
        },
        "tooltip": {
          "mode": "single",
          "sort": "none"
        }
      },
      "pluginVersion": "8.3.7",
      "targets": [
        {
          "datasource": {
            "type": "prometheus",
            "uid": "P1809F7CD0C75ACF3"
          },
          "expr": "avg(histogram_quantile(0.99,irate(ego_client_handle_seconds_bucket{type=\"unary\",app=\"$workload\",kubernetes_namespace=\"$namespace\"}[$summarize])>0)*1000)by(name,method)",
          "hide": false,
          "refId": "B"
        }
      ],
      "title": "gRPC 客户端  P99",
      "type": "timeseries"
    }
  ],
  "refresh": "",
  "schemaVersion": 36,
  "style": "dark",
  "tags": [],
  "templating": {
    "list": [
      {
        "current": {
          "selected": false,
          "text": "prometheus",
          "value": "prometheus"
        },
        "hide": 0,
        "includeAll": false,
        "label": "数据源",
        "multi": false,
        "name": "data_source",
        "options": [],
        "query": "prometheus",
        "queryValue": "",
        "refresh": 1,
        "regex": "",
        "skipUrlSync": false,
        "type": "datasource"
      },
      {
        "current": {
          "selected": false,
          "text": "svc-file",
          "value": "svc-file"
        },
        "datasource": {
          "type": "prometheus",
          "uid": "${data_source}"
        },
        "definition": "label_values(ego_build_info{},name)",
        "hide": 0,
        "includeAll": false,
        "label": "应用名",
        "multi": false,
        "name": "appname",
        "options": [],
        "query": {
          "query": "label_values(ego_build_info{},name)",
          "refId": "StandardVariableQuery"
        },
        "refresh": 1,
        "regex": "",
        "skipUrlSync": false,
        "sort": 0,
        "tagValuesQuery": "",
        "tagsQuery": "",
        "type": "query",
        "useTags": false
      },
      {
        "current": {
          "selected": false,
          "text": "pro",
          "value": "pro"
        },
        "datasource": {
          "type": "prometheus",
          "uid": "${data_source}"
        },
        "definition": "label_values(ego_build_info{},version)",
        "hide": 0,
        "includeAll": false,
        "label": "环境",
        "multi": false,
        "name": "version",
        "options": [],
        "query": {
          "query": "label_values(ego_build_info{},version)",
          "refId": "StandardVariableQuery"
        },
        "refresh": 1,
        "regex": "",
        "skipUrlSync": false,
        "sort": 0,
        "tagValuesQuery": "",
        "tagsQuery": "",
        "type": "query",
        "useTags": false
      },
      {
        "current": {
          "selected": false,
          "text": "smpro-svc-file",
          "value": "smpro-svc-file"
        },
        "datasource": {
          "type": "prometheus",
          "uid": "${data_source}"
        },
        "definition": "label_values(ego_build_info{name=~'$appname', version=~'$version'},app)",
        "description": "Deployment 的 labels.app 值",
        "hide": 0,
        "includeAll": false,
        "label": "labels.app",
        "multi": false,
        "name": "workload",
        "options": [],
        "query": {
          "query": "label_values(ego_build_info{name=~'$appname', version=~'$version'},app)",
          "refId": "StandardVariableQuery"
        },
        "refresh": 2,
        "regex": "",
        "skipUrlSync": false,
        "sort": 0,
        "tagValuesQuery": "",
        "tagsQuery": "",
        "type": "query",
        "useTags": false
      },
      {
        "current": {
          "selected": true,
          "text": [
            "All"
          ],
          "value": [
            "$__all"
          ]
        },
        "datasource": {
          "type": "prometheus",
          "uid": "${data_source}"
        },
        "definition": "label_values(ego_build_info{name=~'$appname', version=~'$version',app='$workload'},kubernetes_pod_name)",
        "hide": 0,
        "includeAll": true,
        "label": "实例",
        "multi": true,
        "name": "instance",
        "options": [],
        "query": {
          "query": "label_values(ego_build_info{name=~'$appname', version=~'$version',app='$workload'},kubernetes_pod_name)",
          "refId": "StandardVariableQuery"
        },
        "refresh": 2,
        "regex": "",
        "skipUrlSync": false,
        "sort": 0,
        "tagValuesQuery": "",
        "tagsQuery": "",
        "type": "query",
        "useTags": false
      },
      {
        "auto": false,
        "auto_count": 30,
        "auto_min": "10s",
        "current": {
          "selected": false,
          "text": "5m",
          "value": "5m"
        },
        "hide": 0,
        "name": "summarize",
        "options": [
          {
            "selected": false,
            "text": "2m",
            "value": "2m"
          },
          {
            "selected": true,
            "text": "5m",
            "value": "5m"
          },
          {
            "selected": false,
            "text": "10m",
            "value": "10m"
          }
        ],
        "query": "2m,5m,10m",
        "queryValue": "",
        "refresh": 2,
        "skipUrlSync": false,
        "type": "interval"
      },
      {
        "current": {
          "selected": true,
          "text": [
            "All"
          ],
          "value": [
            "$__all"
          ]
        },
        "datasource": {
          "type": "prometheus",
          "uid": "${data_source}"
        },
        "definition": "label_values(ego_server_handle_seconds_count{app=~'.*$appname', version=~'$version'},method)",
        "hide": 0,
        "includeAll": true,
        "label": "方法名",
        "multi": true,
        "name": "method",
        "options": [],
        "query": {
          "query": "label_values(ego_server_handle_seconds_count{app=~'.*$appname', version=~'$version'},method)",
          "refId": "StandardVariableQuery"
        },
        "refresh": 1,
        "regex": "",
        "skipUrlSync": false,
        "sort": 0,
        "tagValuesQuery": "",
        "tagsQuery": "",
        "type": "query",
        "useTags": false
      },
      {
        "current": {
          "selected": false,
          "text": [
            "default"
          ],
          "value": [
            "default"
          ]
        },
        "datasource": {
          "type": "prometheus",
          "uid": "${data_source}"
        },
        "definition": "label_values(ego_build_info{name=~'$appname', version=~'$version'}, kubernetes_namespace)",
        "hide": 0,
        "includeAll": true,
        "label": "namespace",
        "multi": true,
        "name": "namespace",
        "options": [],
        "query": {
          "query": "label_values(ego_build_info{name=~'$appname', version=~'$version'}, kubernetes_namespace)",
          "refId": "StandardVariableQuery"
        },
        "refresh": 2,
        "regex": "",
        "skipUrlSync": false,
        "sort": 0,
        "tagValuesQuery": "",
        "tagsQuery": "",
        "type": "query",
        "useTags": false
      },
      {
        "current": {
          "selected": false,
          "text": [
            "All"
          ],
          "value": [
            "$__all"
          ]
        },
        "description": "服务端错误码",
        "hide": 2,
        "includeAll": true,
        "multi": true,
        "name": "server_error_code",
        "options": [
          {
            "selected": true,
            "text": "All",
            "value": "$__all"
          },
          {
            "selected": false,
            "text": "Internal Server Error",
            "value": "Internal Server Error"
          },
          {
            "selected": false,
            "text": "Not Implemented",
            "value": "Not Implemented"
          },
          {
            "selected": false,
            "text": "Bad Gateway",
            "value": "Bad Gateway"
          },
          {
            "selected": false,
            "text": "Service Unavailable",
            "value": "Service Unavailable"
          },
          {
            "selected": false,
            "text": "Gateway Timeout",
            "value": "Gateway Timeout"
          },
          {
            "selected": false,
            "text": "HTTP Version Not Supported",
            "value": "HTTP Version Not Supported"
          },
          {
            "selected": false,
            "text": "Variant Also Negotiates",
            "value": "Variant Also Negotiates"
          },
          {
            "selected": false,
            "text": "Insufficient Storage",
            "value": "Insufficient Storage"
          },
          {
            "selected": false,
            "text": "Loop Detected",
            "value": "Loop Detected"
          },
          {
            "selected": false,
            "text": "Not Extended",
            "value": "Not Extended"
          },
          {
            "selected": false,
            "text": "Network Authentication Required",
            "value": "Network Authentication Required"
          }
        ],
        "query": "Internal Server Error,Not Implemented,Bad Gateway,Service Unavailable,Gateway Timeout,HTTP Version Not Supported,Variant Also Negotiates,Insufficient Storage,Loop Detected,Not Extended,Network Authentication Required",
        "queryValue": "",
        "skipUrlSync": false,
        "type": "custom"
      }
    ]
  },
  "time": {
    "from": "now-30m",
    "to": "now"
  },
  "timepicker": {
    "refresh_intervals": [
      "10s",
      "30s",
      "1m",
      "5m"
    ],
    "time_options": [
      "5m",
      "15m",
      "1h",
      "6h",
      "12h",
      "24h",
      "2d",
      "7d",
      "30d"
    ]
  },
  "timezone": "",
  "title": "overview",
  "uid": "overview",
  "version": 156,
  "weekStart": ""
}